pypond/__init__.py
pypond/bases.py
pypond/collection.py
pypond/event.py
pypond/exceptions.py
pypond/functions.py
pypond/index.py
pypond/indexed_event.py
pypond/pipeline.py
pypond/range.py
pypond/series.py
pypond/timerange_event.py
pypond/util.py
pypond/io/__init__.py
pypond/io/input.py
pypond/io/output.py
pypond/processor/__init__.py
pypond/processor/aggregator.py
pypond/processor/align.py
pypond/processor/base.py
pypond/processor/collapser.py
pypond/processor/converter.py
pypond/processor/filler.py
pypond/processor/filter.py
pypond/processor/mapper.py
pypond/processor/offset.py
pypond/processor/rate.py
pypond/processor/selector.py
pypond/processor/taker.py
pypond-0.5.3.dist-info/licenses/LICENSE.txt
pypond-0.5.3.dist-info/METADATA
pypond-0.5.3.dist-info/WHEEL
pypond-0.5.3.dist-info/top_level.txt
pypond-0.5.3.dist-info/RECORD
