Metadata-Version: 2.4
Name: pypond
Version: 0.5.3
Summary: Python implementation of the Pond JavaScript timeseries library (https://github.com/esnet/pond).
Home-page: https://github.com/esnet/pypond
Author: Monte M. Goode
Author-email: tools@es.net
Classifier: Development Status :: 4 - Beta
Classifier: Intended Audience :: Developers
Classifier: Environment :: Console
Classifier: Environment :: Web Environment
Classifier: License :: OSI Approved :: BSD License
Classifier: Operating System :: POSIX
Classifier: Programming Language :: Python :: 2.7
Classifier: Programming Language :: Python :: 3.3
Classifier: Programming Language :: Python :: 3.4
Classifier: Programming Language :: Python :: 3.5
Classifier: Programming Language :: Python :: 3.6
Classifier: Programming Language :: Python :: 3.10
Classifier: Programming Language :: JavaScript
Classifier: Topic :: Software Development :: Libraries
License-File: LICENSE.txt
Requires-Dist: pyrsistent==0.20.0
Requires-Dist: pytz>=2016.4
Requires-Dist: tzlocal==5.3
Requires-Dist: humanize==4.12.1
Requires-Dist: six>=1.10.0
Requires-Dist: sphinxcontrib-napoleon==0.7
Requires-Dist: recommonmark==0.7.1
Dynamic: author
Dynamic: author-email
Dynamic: classifier
Dynamic: description
Dynamic: home-page
Dynamic: license-file
Dynamic: requires-dist
Dynamic: summary
